disposable_email_validator/__init__.py
disposable_email_validator/disposable_emails
disposable_email_validator/validator.py
disposable_email_validator-0.0.8.data/data/disposable_emails
disposable_email_validator-0.0.8.dist-info/LICENSE
disposable_email_validator-0.0.8.dist-info/METADATA
disposable_email_validator-0.0.8.dist-info/WHEEL
disposable_email_validator-0.0.8.dist-info/top_level.txt
disposable_email_validator-0.0.8.dist-info/RECORD
