Metadata-Version: 2.1
Name: disposable_email_validator
Version: 0.0.8
Summary: Python library for disposable email validation
Home-page: https://github.com/2dlab/disposable-email-validator
Author: Gusarov Vladislav
Author-email: tech@2dlab.ru
License: UNKNOWN
Platform: UNKNOWN
Classifier: Programming Language :: Python :: 3
Classifier: License :: OSI Approved :: MIT License
Classifier: Operating System :: OS Independent
Requires-Python: >=3.6
License-File: LICENSE
